{
  "ticker": "BSPB",
  "date": "2026-02-11",
  "shortname": "БСП ао",
  "secname": "ПАО \"Банк \"Санкт-Петербург\" ао",
  "price": {
    "last": 325.1,
    "open": 319.11,
    "high": 326.5,
    "low": 319.02,
    "waprice": 323.63,
    "prev_close": 319.11
  },
  "volume": {
    "shares_today": 245600,
    "value_today_rub": 79484311,
    "num_trades_today": 3733
  },
  "liquidity": {
    "adv_30d_rub": 176178209,
    "adv_30d_mln_rub": 176.2,
    "bid_ask_spread_pct": 0.0092
  },
  "capitalization": {
    "market_cap_rub": 144767037751.05,
    "market_cap_bln_rub": 144.8,
    "shares_outstanding": 445368521
  },
  "range_52w": {
    "high": 416.97,
    "low": 299.9
  },
  "listing": {
    "board": "TQBR",
    "list_level": 1,
    "lot_size": 10
  }
}
