{
  "ticker": "MTSS",
  "company_name": "МТС",
  "date": "2026-02-19",
  "dividends": [
    {
      "registryclosedate": "2018-07-09",
      "value": 23.4,
      "currencyid": "RUB"
    },
    {
      "registryclosedate": "2018-10-09",
      "value": 2.6,
      "currencyid": "RUB"
    },
    {
      "registryclosedate": "2019-07-09",
      "value": 19.98,
      "currencyid": "RUB"
    },
    {
      "registryclosedate": "2019-10-14",
      "value": 8.68,
      "currencyid": "RUB"
    },
    {
      "registryclosedate": "2020-01-10",
      "value": 13.25,
      "currencyid": "RUB"
    },
    {
      "registryclosedate": "2020-07-09",
      "value": 20.57,
      "currencyid": "RUB"
    },
    {
      "registryclosedate": "2020-10-12",
      "value": 8.93,
      "currencyid": "RUB"
    },
    {
      "registryclosedate": "2021-07-08",
      "value": 26.51,
      "currencyid": "RUB"
    },
    {
      "registryclosedate": "2021-10-12",
      "value": 10.55,
      "currencyid": "RUB"
    },
    {
      "registryclosedate": "2022-07-12",
      "value": 33.85,
      "currencyid": "RUB"
    },
    {
      "registryclosedate": "2023-06-29",
      "value": 34.29,
      "currencyid": "RUB"
    },
    {
      "registryclosedate": "2024-07-16",
      "value": 35,
      "currencyid": "RUB"
    },
    {
      "registryclosedate": "2025-07-07",
      "value": 35,
      "currencyid": "RUB"
    }
  ],
  "ir_events": []
}
