[
  {
    "date": "2026-03-01",
    "trigger": "Индия может начать закупать больше российской нефти, считает эксперт — дубль кластера Ормуз",
    "trigger_url": "https://ria.ru/20260301/indija-2077734118.html",
    "signal": "skip",
    "direction": "skip",
    "confidence": "low",
    "entry": null,
    "exit": null,
    "expected_return_pct": null,
    "risk_reward_ratio": null,
    "position_size": "skip",
    "reasoning": "Noise: экспертное мнение о гипотетическом росте закупок российской нефти Индией — дубль кластера Ормуз (уже покрыт 9 сигналами). Позитив в цене: +4.5% от пре-новостного уровня (5147→5376.5), volume ~2x ADV. R/R = 1.53 (upside 15.3% до fair value 6200, stop −10% = 4839) < минимума 2.0. Ожидаем FY2025 МСФО 4 марта — более значимый катализатор."
  },
  {
    "date": "2026-03-01",
    "trigger": "Прогноз роста цен на нефть после перекрытия Ормузского пролива — возможен переход Китая и Индии на российскую нефть",
    "trigger_url": "https://lenta.ru/news/2026/03/01/tsenam-na-neft-sprognozirovali-rost-posle-perekrytiya-iranom-ormuzskogo-proliva/",
    "signal": "skip",
    "direction": "skip",
    "confidence": "low",
    "entry": null,
    "exit": null,
    "expected_return_pct": null,
    "risk_reward_ratio": null,
    "position_size": "skip",
    "reasoning": "Аналитический прогноз (noise) в рамках кластера Ормуз — не самостоятельный катализатор. Позитив уже в цене: +4.5% от пре-новостного уровня (5147→5376.5), volume ~2x ADV. R/R = 1.53 (upside 15.3% до fair value 6200, stop −10% = 4839) < минимума 2.0. Ожидаем FY2025 МСФО 4 марта."
  },
  {
    "date": "2026-03-01",
    "trigger": "Эскалация вокруг Ормузского пролива может поддержать цены на нефть и газ — Investing.com",
    "trigger_url": "https://ru.investing.com/news/economy-news/article-3133381",
    "signal": "skip",
    "direction": "skip",
    "confidence": "low",
    "entry": null,
    "exit": null,
    "expected_return_pct": null,
    "risk_reward_ratio": null,
    "position_size": "skip",
    "reasoning": "Продолжение геополитического кластера (Ормуз), уже покрытого 5 сигналами. Позитив в цене: +4.5% от пре-новостного уровня (5147→5376.5), volume ~2x ADV. R/R = 1.53 (upside 15.3% до fair value 6200, stop −10% = 4839) < минимума 2.0. Временный макро-фактор, не меняет фундаментальный тезис (neutral/hold). Ожидаем FY2025 МСФО 4 марта — более значимый катализатор."
  },
  {
    "date": "2026-03-01",
    "trigger": "ОПЕК+ увеличит добычу нефти с апреля на 206 000 б/с — дополнительное предложение давит на цены",
    "trigger_url": "https://www.vedomosti.ru/business/news/2026/03/01/1179887-opek-uvelichit-dobichu",
    "signal": "skip",
    "direction": "skip",
    "confidence": "low",
    "entry": null,
    "exit": null,
    "expected_return_pct": null,
    "risk_reward_ratio": null,
    "position_size": "skip",
    "reasoning": "Негативная макро-новость (ОПЕК+ +206k б/с с апреля), но цена +3.5% за день на геополитике (Ормуз). Ни long-positive (новость негативная), ни long-oversold (цена не упала) — нет сценария. Увеличение добычи скромное, усиливает уже известный key_risk (Urals под давлением), тезис не сломан. R/R = 1.53 < 2.0."
  },
  {
    "date": "2026-03-01",
    "trigger": "Азиатские покупатели иранской нефти (Китай, Индия) могут перейти на российскую нефть при затяжном конфликте вокруг Ормузского пролива",
    "trigger_url": "https://1prime.ru/20260301/neft-867916916.html",
    "signal": "skip",
    "direction": "skip",
    "confidence": "low",
    "entry": null,
    "exit": null,
    "expected_return_pct": null,
    "risk_reward_ratio": null,
    "position_size": "skip",
    "reasoning": "Продолжение геополитического кластера (Ормузский пролив). Позитив уже в цене: +3.5% от пре-новостного уровня (5194→5376.5), volume ~2x ADV. R/R = 1.53 (upside 15.3% до fair value 6200, stop −10% = 4839) < минимума 2.0. Макро-фактор не специфичен для ЛУКОЙЛ, переключение азиатских покупателей — спекулятивный сценарий. Ближайший катализатор — FY2025 МСФО 4 марта."
  },
  {
    "date": "2026-03-01",
    "trigger": "Иран закрыл Ормузский пролив — ~200 танкеров скопились, Brent $73.21, ЛУКОЙЛ +3.5% за 2 дня",
    "trigger_url": "https://lenta.ru/news/2026/03/01/ne-proydet/",
    "signal": "skip",
    "direction": "skip",
    "confidence": "low",
    "entry": null,
    "exit": null,
    "expected_return_pct": null,
    "risk_reward_ratio": null,
    "position_size": "skip",
    "reasoning": "Эскалация на Ближнем Востоке (закрытие Ормузского пролива, ~200 танкеров заблокированы) — продолжение ударов по Ирану 28.02. Цена +3.5% от пре-новостного уровня (5194→5376.5), volume ~2x ADV — частично в цене. R/R = 1.53 (upside 15.3% до fair value 6200, stop −10% = 4839) < минимума 2.0. Временный макро-фактор, не меняет фундаментальный тезис (neutral/hold). Ожидаем FY2025 МСФО 4 марта — основной катализатор."
  },
  {
    "date": "2026-03-01",
    "trigger": "Индекс МосБиржи >2800 на фоне эскалации Ближний Восток — Иран перекрыл Ормузский пролив, ЛУКОЙЛ +2.99%",
    "trigger_url": "https://www.finam.ru/publications/item/indeks-mosbirzhi-prevysil-2800-punktov-na-fone-eskalatsii-na-blizhnem-vostoke-20260301-1037/",
    "signal": "skip",
    "direction": "skip",
    "confidence": "low",
    "entry": null,
    "exit": null,
    "expected_return_pct": null,
    "risk_reward_ratio": null,
    "position_size": "skip",
    "reasoning": "Продолжение геополитического триггера (Иран), уже покрытого сигналом от 28.02. Цена +4.5% от пре-новостного уровня (5147→5376.5), volume ~2x ADV — частично в цене. R/R = 1.53 < 2.0. Временный макро-фактор, не меняет фундаментальный тезис (neutral/hold). Ближайший катализатор — FY2025 МСФО 4 марта."
  },
  {
    "date": "2026-03-01",
    "trigger": "Аналитики считают укрепление рубля временным, прогноз ослабления к 80–100 ₽/$ к осени — позитив для экспортёров",
    "trigger_url": "https://1prime.ru/20260301/rubl-867911597.html",
    "signal": "skip",
    "direction": "skip",
    "confidence": "low",
    "entry": null,
    "exit": null,
    "expected_return_pct": null,
    "risk_reward_ratio": null,
    "position_size": "skip",
    "reasoning": "Общая макро-новость, не специфичная для ЛУКОЙЛ (компания упомянута лишь как пример экспортёра). Ослабление рубля уже заложено в key_opportunities. Цена 1 марта +3.5% при volume ~2x ADV — движение, вероятно, связано с ожиданием FY2025 МСФО (4 марта), а не с этой новостью. Позитив уже в цене."
  },
  {
    "date": "2026-02-28",
    "trigger": "Удары США и Израиля по Ирану вызвали рост нефти Brent (+2.7% до $72.76), акции ЛУКОЙЛ +2.6% 28 фев, +3.5% 1 мар",
    "trigger_url": "https://smart-lab.ru/blog/1271073.php",
    "signal": "skip",
    "direction": "skip",
    "confidence": "low",
    "entry": null,
    "exit": null,
    "expected_return_pct": null,
    "risk_reward_ratio": null,
    "position_size": "skip",
    "reasoning": "Геополитический шок (Иран) — временный макро-фактор, не компанийный катализатор. Цена +4.5% от уровня до новости (5147→5376.5), volume ~2x ADV — частично в цене. R/R = 1.53 (upside 15.3% до fair value 6200, stop -10%) < минимума 2.0. Sentiment neutral, position hold — недостаточный upside для входа на временном факторе. Ближайший катализатор — FY2025 МСФО 4 марта."
  },
  {
    "date": "2026-02-27",
    "trigger": "Скачок цен на нефть Brent +2.7% до $72.76, акции ЛУКОЙЛ +1.47% — начало ралли на ближневосточной напряжённости",
    "trigger_url": "https://www.finam.ru/publications/item/skachok-tsen-na-neft-okazal-podderzhku-rossiyskomu-rynku-aktsii-lukoyla-vyrosli-na-15-20260227-1928/",
    "signal": "skip",
    "direction": "skip",
    "confidence": "low",
    "entry": null,
    "exit": null,
    "expected_return_pct": null,
    "risk_reward_ratio": null,
    "position_size": "skip",
    "reasoning": "Обзорная статья — ЛУКОЙЛ не главный герой, упомянут как бенефициар роста нефти. Прекурсор ударов по Ирану 28.02. Позитив далее усилился (Ормуз) и уже в цене: +4.5% от 5147 до 5376.5, volume ~2x ADV. R/R = 1.53 < 2.0."
  },
  {
    "date": "2026-02-26",
    "trigger": "Litasco начала арбитраж против Болгарии ($4.5 млрд за экспроприацию НПЗ); дочка ЛУКОЙЛа подала иск к Румынии (проект Trident); TotalEnergies выкупила 45% НПЗ у ЛУКОЙЛа — продолжение потери зарубежных активов",
    "trigger_url": "https://www.kommersant.ru/doc/8461756",
    "signal": "skip",
    "direction": "skip",
    "confidence": "low",
    "entry": null,
    "exit": null,
    "expected_return_pct": null,
    "risk_reward_ratio": null,
    "position_size": "skip",
    "reasoning": "Кластер негативных новостей подтверждает уже известные key_risks (SDN-санкции, потеря зарубежных активов). Цена −1.1% на низком объёме (volume <1x ADV) — рынок не отреагировал. Нет условий для long-oversold (падение <2%), нет условий для long-positive (новость негативная). Тезис не сломан — иски к Румынии/Болгарии и продажа НПЗ уже заложены в fair value 6200. R/R при входе по текущей цене = 1.53 < 2.0."
  }
]
