[
  {
    "date": "2026-02-24",
    "title": "Как нефтегазовые компании отчитаются по итогам 2025 года",
    "type": "news",
    "url": "https://smart-lab.ru/blog/1269238.php",
    "impact": "neutral",
    "summary": "Статья содержит прогноз финансовых показателей Татнефти на 2025 год: ожидается снижение выручки на 17% г/г, EBITDA на 23%, чистой прибыли на 20%. Однако авторы отмечают, что Татнефть относится к наиболее устойчивым компаниям сектора благодаря высоким ценам на нефтепродукты и эффекту курсовых разниц. Прогноз дивидендов 15 руб./акцию (2.8% доходность) — умеренно позитивный сигнал относительно других игроков с большим падением прибыли.",
    "strength": "medium",
    "action": "hold",
    "source": "rss-feeder"
  }
]